ublox/__init__.py
ublox/modules.py
ublox/socket.py
ublox-0.1.3.dist-info/LICENSE.txt
ublox-0.1.3.dist-info/METADATA
ublox-0.1.3.dist-info/RECORD
ublox-0.1.3.dist-info/WHEEL
ublox-0.1.3.dist-info/top_level.txt
