Metadata-Version: 2.1
Name: ublox
Version: 0.1.3
Summary: Python library for U-blox cellular modules.
Home-page: https://github.com/pwitab/ublox
Author: Henrik Palmlund Wahlgren @ Palmlund Wahlgren Innovative Technology AB
Author-email: henrik@pwit.se
License: MIT
Keywords: NB-IoT,LTE-M
Platform: UNKNOWN
Requires-Python: ~=3.6
Requires-Dist: pyserial
